[
    {
        "id": 1,
        "nome": "Butt Knight",
        "caminho_executavel": "F:\\Projetos 5 Royal\\Jogos\\Butt Knight\\ButtKnight-Cracked\\ButtKnight\\ButtKnight.exe",
        "caminho_pasta": "F:\\Projetos 5 Royal\\Jogos\\Butt Knight",
        "tamanho_gb": null,
        "imagem_capa": null,
        "imagem_fundo": null,
        "imagens_extras": [],
        "descricao": null,
        "desenvolvedor": null,
        "studio": null,
        "engine": null,
        "versao": null,
        "links": [],
        "genero": null,
        "tags": [],
        "colecoes": [
            "rpgs-favoritos"
        ],
        "tempo_jogado_segundos": 0,
        "ultima_vez_jogado": null,
        "status": "N\u00e3o Jogado",
        "zerado": false,
        "jogar_mais_tarde": false,
        "review_texto": null,
        "avaliacao_detalhada": null
    },
    {
        "id": 2,
        "nome": "Dungeon Vixen",
        "caminho_executavel": "F:\\Projetos 5 Royal\\Jogos\\Dungeon Vixen\\DungeonVixens [1.1.7]\\DungeonVixens.exe",
        "caminho_pasta": "F:\\Projetos 5 Royal\\Jogos\\Dungeon Vixen",
        "tamanho_gb": null,
        "imagem_capa": null,
        "imagem_fundo": null,
        "imagens_extras": [],
        "descricao": null,
        "desenvolvedor": null,
        "studio": null,
        "engine": null,
        "versao": null,
        "links": [],
        "genero": null,
        "tags": [],
        "colecoes": [],
        "tempo_jogado_segundos": 0,
        "ultima_vez_jogado": null,
        "status": "N\u00e3o Jogado",
        "zerado": false,
        "jogar_mais_tarde": false,
        "review_texto": null,
        "avaliacao_detalhada": null
    },
    {
        "id": 3,
        "nome": "Fear and Hungersssssss",
        "caminho_executavel": "F:\\Projetos 5 Royal\\Jogos\\Fear and Hunger\\FH_Ver.1.4.1\\Fear & Hunger Ver.1.4.1\\Game.exe",
        "caminho_pasta": "F:\\Projetos 5 Royal\\Jogos\\Fear and Hunger",
        "tamanho_gb": null,
        "imagem_capa": null,
        "imagem_fundo": null,
        "imagens_extras": [],
        "descricao": null,
        "desenvolvedor": "aqls caras",
        "studio": null,
        "engine": null,
        "versao": null,
        "links": [],
        "genero": null,
        "tags": [
            "porno"
        ],
        "colecoes": [
            "rpgs-favoritos"
        ],
        "tempo_jogado_segundos": 0,
        "ultima_vez_jogado": null,
        "status": "N\u00e3o Jogado",
        "zerado": false,
        "jogar_mais_tarde": false,
        "review_texto": null,
        "avaliacao_detalhada": null
    },
    {
        "id": 4,
        "nome": "Renryuu Ascension",
        "caminho_executavel": "F:\\Projetos 5 Royal\\Jogos\\Renryuu Ascension\\Renryuu Acension\\Renryuu Ascension 25.04.09 [Windows Version]\\Game.exe",
        "caminho_pasta": "F:\\Projetos 5 Royal\\Jogos\\Renryuu Ascension",
        "tamanho_gb": null,
        "imagem_capa": null,
        "imagem_fundo": null,
        "imagens_extras": [],
        "descricao": null,
        "desenvolvedor": null,
        "studio": null,
        "engine": null,
        "versao": null,
        "links": [],
        "genero": null,
        "tags": [],
        "colecoes": [],
        "tempo_jogado_segundos": 0,
        "ultima_vez_jogado": null,
        "status": "N\u00e3o Jogado",
        "zerado": false,
        "jogar_mais_tarde": false,
        "review_texto": null,
        "avaliacao_detalhada": null
    },
    {
        "id": 5,
        "nome": "Ricoche A Weak JK's Climactic Battle",
        "caminho_executavel": "F:\\Projetos 5 Royal\\Jogos\\Ricoche A Weak JK's Climactic Battle\\Ricoche_A_Weak_JKs_Climactic_Battle_With_Orcs\\Ricoche A Weak JK's Climactic Battle With Orcs\\Game.exe",
        "caminho_pasta": "F:\\Projetos 5 Royal\\Jogos\\Ricoche A Weak JK's Climactic Battle",
        "tamanho_gb": null,
        "imagem_capa": null,
        "imagem_fundo": null,
        "imagens_extras": [],
        "descricao": null,
        "desenvolvedor": null,
        "studio": null,
        "engine": null,
        "versao": null,
        "links": [],
        "genero": null,
        "tags": [],
        "colecoes": [],
        "tempo_jogado_segundos": 0,
        "ultima_vez_jogado": null,
        "status": "N\u00e3o Jogado",
        "zerado": false,
        "jogar_mais_tarde": false,
        "review_texto": null,
        "avaliacao_detalhada": null
    },
    {
        "id": 6,
        "nome": "Succubus Connect",
        "caminho_executavel": "F:\\Projetos 5 Royal\\Jogos\\Succubus Connect\\SuccubusConnect_Final_capture1\\Game.exe",
        "caminho_pasta": "F:\\Projetos 5 Royal\\Jogos\\Succubus Connect",
        "tamanho_gb": null,
        "imagem_capa": null,
        "imagem_fundo": null,
        "imagens_extras": [],
        "descricao": null,
        "desenvolvedor": null,
        "studio": null,
        "engine": null,
        "versao": null,
        "links": [],
        "genero": null,
        "tags": [],
        "colecoes": [],
        "tempo_jogado_segundos": 0,
        "ultima_vez_jogado": null,
        "status": "N\u00e3o Jogado",
        "zerado": false,
        "jogar_mais_tarde": false,
        "review_texto": null,
        "avaliacao_detalhada": null
    },
    {
        "id": 7,
        "nome": "Under the Witch",
        "caminho_executavel": "F:\\Projetos 5 Royal\\Jogos\\Under the Witch\\Under the Witch\\RJ397236\\RJ397236.part1.exe",
        "caminho_pasta": "F:\\Projetos 5 Royal\\Jogos\\Under the Witch",
        "tamanho_gb": null,
        "imagem_capa": null,
        "imagem_fundo": null,
        "imagens_extras": [],
        "descricao": null,
        "desenvolvedor": null,
        "studio": null,
        "engine": null,
        "versao": null,
        "links": [],
        "genero": null,
        "tags": [],
        "colecoes": [],
        "tempo_jogado_segundos": 0,
        "ultima_vez_jogado": null,
        "status": "N\u00e3o Jogado",
        "zerado": false,
        "jogar_mais_tarde": false,
        "review_texto": null,
        "avaliacao_detalhada": null
    }
]